{"students": [{"id": "1", "name": "A", "totalAverages": 72.03333333333332, "courses": [{"id": "1", "name": "Biology", "teacher": "Mr. D", "courseAverages": 90.1}, {"id": "2", "name": "History", "teacher": " Mrs. P", "courseAverages": 51.8}, {"id": "3", "name": "Math", "teacher": " Mrs. C", "courseAverages": 74.2}]}, {"id": "2", "name": "B", "totalAverages": 72.03333333333332, "courses": [{"id": "1", "name": "Biology", "teacher": "Mr. D", "courseAverages": 90.1}, {"id": "2", "name": "History", "teacher": " Mrs. P", "courseAverages": 51.8}, {"id": "3", "name": "Math", "teacher": " Mrs. C", "courseAverages": 74.2}]}, {"id": "3", "name": "C", "totalAverages": 72.03333333333332, "courses": [{"id": "1", "name": "Biology", "teacher": "Mr. D", "courseAverages": 90.1}, {"id": "2", "name": "History", "teacher": " Mrs. P", "courseAverages": 51.8}, {"id": "3", "name": "Math", "teacher": " Mrs. C", "courseAverages": 74.2}]}]}